smtpproto/__init__.py
smtpproto/_utils.py
smtpproto/auth.py
smtpproto/client.py
smtpproto/protocol.py
smtpproto/py.typed
smtpproto-2.0.0.dist-info/LICENSE
smtpproto-2.0.0.dist-info/METADATA
smtpproto-2.0.0.dist-info/WHEEL
smtpproto-2.0.0.dist-info/top_level.txt
smtpproto-2.0.0.dist-info/RECORD
