Metadata-Version: 2.1
Name: smtpproto
Version: 2.0.0
Summary: Sans-io SMTP client with an AnyIO based async I/O implementation
Author-email: Alex Grönholm <alex.gronholm@nextday.fi>
License: MIT
Project-URL: Documentation, https://smtpproto.readthedocs.io/en/latest/
Project-URL: Source code, https://github.com/agronholm/smtpproto
Project-URL: Issue tracker, https://github.com/agronholm/smtpproto/issues
Classifier: Development Status :: 5 - Production/Stable
Classifier: Intended Audience :: Developers
Classifier: License :: OSI Approved :: MIT License
Classifier: Typing :: Typed
Classifier: Framework :: AnyIO
Classifier: Topic :: Communications :: Email
Classifier: Programming Language :: Python
Classifier: Programming Language :: Python :: 3
Classifier: Programming Language :: Python :: 3.8
Classifier: Programming Language :: Python :: 3.9
Classifier: Programming Language :: Python :: 3.10
Classifier: Programming Language :: Python :: 3.11
Classifier: Programming Language :: Python :: 3.12
Requires-Python: >=3.8
License-File: LICENSE
Requires-Dist: anyio ~=4.2
Provides-Extra: doc
Requires-Dist: packaging ; extra == 'doc'
Requires-Dist: sphinx-rtd-theme >=1.3.0 ; extra == 'doc'
Requires-Dist: sphinx-autodoc-typehints >=1.2.0 ; extra == 'doc'
Provides-Extra: test
Requires-Dist: anyio[trio] >=3.0 ; extra == 'test'
Requires-Dist: aiosmtpd >=1.4.4 ; extra == 'test'
Requires-Dist: coverage >=7 ; extra == 'test'
Requires-Dist: pytest >=6.0 ; extra == 'test'
Requires-Dist: trustme ; extra == 'test'
